README.md
setup.py
astr2600/__init__.py
astr2600/atmosphere.py
astr2600/cmaps.py
astr2600/galileo.py
astr2600/rectangles.py
astr2600/resample.py
astr2600/rover.py
astr2600/sdss.py
astr2600/solarsystem.py
astr2600/topography.py
astr2600/version.py
astr2600/nbody/__init__.py
astr2600/nbody/systems.py
cu_astr2600.egg-info/PKG-INFO
cu_astr2600.egg-info/SOURCES.txt
cu_astr2600.egg-info/dependency_links.txt
cu_astr2600.egg-info/not-zip-safe
cu_astr2600.egg-info/requires.txt
cu_astr2600.egg-info/top_level.txt