Metadata-Version: 1.1
Name: cu-astr2600
Version: 0.11.0
Summary: A collection of toys and tools for ASTR2600 at CU Boulder.
Home-page: https://github.com/zkbt/cu-astr2600
Author: Zach Berta-Thompson
Author-email: zach.bertathompson@colorado.edu
License: MIT
Platform: UNKNOWN
Classifier: Intended Audience :: Education
Classifier: Intended Audience :: Science/Research
Classifier: Programming Language :: Python
Classifier: Topic :: Scientific/Engineering :: Astronomy
